pyzh/__init__.py
pyzh/内置函数.py
pyzh/函数方法.py
pyzh/对象属性.py
pyzh/对象类.py
pyzh/工具函数.py
pyzh/序列操作.py
pyzh/异常处理.py
pyzh/数值运算.py
pyzh/文件操作.py
pyzh/类型转换.py
pyzh/编译执行.py
pyzh/输入输出.py
pyzh/迭代生成.py
pyzh/逻辑判断.py
pyzh/集合操作.py
pyzh/魔法方法.py
pyzh-0.1.2.dist-info/LICENSE
pyzh-0.1.2.dist-info/METADATA
pyzh-0.1.2.dist-info/WHEEL
pyzh-0.1.2.dist-info/top_level.txt
pyzh-0.1.2.dist-info/RECORD
