Metadata-Version: 2.2
Name: pyzh
Version: 0.1.2
Summary: Python中文编程包，让中文用户使用自然语法进行Python编程
Home-page: https://github.com/Tech-Six/Pyzh
Author: Tech-Six
Author-email: contact@techsix.org
Project-URL: Bug Tracker, https://github.com/Tech-Six/Pyzh
Project-URL: Documentation, https://github.com/Tech-Six/Pyzh
Project-URL: Source Code, https://github.com/Tech-Six/Pyzh
Project-URL: Homepage, https://github.com/Tech-Six/Pyzh
Keywords: chinese,programming,education,learning,python,pyzh,y中文模块,中文编程,编程教育,计算机教育,编程入门,中文函数,
Classifier: Programming Language :: Python :: 3
Classifier: Programming Language :: Python :: 3.7
Classifier: Programming Language :: Python :: 3.8
Classifier: Programming Language :: Python :: 3.9
Classifier: Programming Language :: Python :: 3.10
Classifier: Programming Language :: Python :: 3.11
Classifier: Programming Language :: Python :: 3.12
Classifier: Programming Language :: Python :: 3.13
Classifier: License :: OSI Approved :: MIT License
Classifier: Operating System :: OS Independent
Classifier: Natural Language :: Chinese (Simplified)
Classifier: Intended Audience :: Education
Classifier: Intended Audience :: Developers
Classifier: Topic :: Education
Classifier: Topic :: Software Development :: Libraries :: Python Modules
Requires-Python: >=3.7
License-File: LICENSE
Requires-Dist: jieba>=0.42.1
Dynamic: author
Dynamic: author-email
Dynamic: classifier
Dynamic: description
Dynamic: description-content-type
Dynamic: home-page
Dynamic: keywords
Dynamic: project-url
Dynamic: requires-dist
Dynamic: requires-python
Dynamic: summary
